henxel/__init__.py
henxel/__main__.py
henxel/changefont.py
henxel/decorators.py
henxel/editor.png
henxel/fdialog.py
henxel/help.txt
henxel/printer.py
henxel/settings.py
henxel/shortcuts.txt
henxel/shortcuts_mac.txt
henxel/wordexpand.py
henxel-0.3.5.dist-info/licenses/LICENSE
importflags/__init__.py
henxel-0.3.5.dist-info/METADATA
henxel-0.3.5.dist-info/WHEEL
henxel-0.3.5.dist-info/entry_points.txt
henxel-0.3.5.dist-info/top_level.txt
henxel-0.3.5.dist-info/RECORD
