Metadata-Version: 2.4
Name: henxel
Version: 0.3.5
Summary: GUI-editor for Python development.
Author-email: SamuelKos <koskinens371@gmail.com>
Project-URL: Homepage, https://github.com/SamuelKos/henxel
Project-URL: Changelog, https://github.com/SamuelKos/henxel/blob/main/CHANGELOG
Keywords: henxel,editor,editors,tkinter,GUI
Classifier: Programming Language :: Python :: 3
Classifier: License :: OSI Approved :: GNU General Public License v3 (GPLv3)
Classifier: Operating System :: Microsoft :: Windows
Classifier: Operating System :: POSIX :: Linux
Classifier: Operating System :: MacOS
Classifier: Intended Audience :: Developers
Classifier: Topic :: Software Development
Classifier: Topic :: Text Editors
Requires-Python: >=3.9
License-File: LICENSE
Dynamic: license-file
